processador_imagens_wsc/__init__.py
processador_imagens_wsc/processador/__init__.py
processador_imagens_wsc/processador/combinacao.py
processador_imagens_wsc/processador/transformacao.py
processador_imagens_wsc/util/__init__.py
processador_imagens_wsc/util/io.py
processador_imagens_wsc/util/plot.py
processador_imagens_wsc-0.0.1.dist-info/METADATA
processador_imagens_wsc-0.0.1.dist-info/WHEEL
processador_imagens_wsc-0.0.1.dist-info/top_level.txt
processador_imagens_wsc-0.0.1.dist-info/RECORD
