Metadata-Version: 2.1
Name: processador-imagens-wsc
Version: 0.0.1
Summary: Pacote de processamento de imagem com Skimage
Home-page: https://github.com/wscoutinho/dio-processador-imagens
Author: Willian Coutinho
Author-email: williancoutinho@ymail.com
License: UNKNOWN
Platform: UNKNOWN
Requires-Python: >=3.8
Requires-Dist: matplotlib
Requires-Dist: numpy
Requires-Dist: scikit-image
